advstats/__init__.py
advstats/_version.py
advstats/core/__init__.py
advstats/core/api.py
advstats/core/clust.py
advstats/core/strat.py
advstats/tests/__init__.py
advstats/tests/test_clust.py
advstats/tests/test_strat.py
advstats-1.0.dist-info/LICENSE
advstats-1.0.dist-info/METADATA
advstats-1.0.dist-info/WHEEL
advstats-1.0.dist-info/top_level.txt
advstats-1.0.dist-info/RECORD
