Metadata-Version: 2.1
Name: advstats
Version: 1.0
Summary: Libarary for statisical analysis on non-standard sampling methods
Home-page: https://pavanadapa.github.io
Author: Pavan Kumar Adapa
Author-email: pavan.adapa@uconn.edu
License: MIT LICENSE
Project-URL: Bug Tracker, https://github.com/pavanadapa/AdvStats/issues
Project-URL: Documentation, https://pavanadapa.github.io
Project-URL: Source Code, https://github.com/pavanadapa/AdvStats
Platform: any
Classifier: Environment :: Console
Classifier: Intended Audience :: Science/Research
Classifier: License :: OSI Approved :: BSD License
Classifier: Operating System :: OS Independent
Classifier: Topic :: Scientific/Engineering :: Mathematics
Requires-Python: >=3.8
License-File: LICENSE
Requires-Dist: numpy (>=1.23.1)
Requires-Dist: pandas (>=1.4.3)
